.coveragerc
.editorconfig
.gitignore
.travis.yml
AUTHORS.rst
CONTRIBUTING.rst
HISTORY.rst
LICENSE
MANIFEST.in
Makefile
README.rst
manage.py
requirements.txt
requirements_dev.txt
requirements_test.txt
runtests.py
setup.cfg
setup.py
tox.ini
.github/ISSUE_TEMPLATE.md
dj_fiobank_payments/__init__.py
dj_fiobank_payments/admin.py
dj_fiobank_payments/apps.py
dj_fiobank_payments/models.py
dj_fiobank_payments/statement.py
dj_fiobank_payments.egg-info/PKG-INFO
dj_fiobank_payments.egg-info/SOURCES.txt
dj_fiobank_payments.egg-info/dependency_links.txt
dj_fiobank_payments.egg-info/not-zip-safe
dj_fiobank_payments.egg-info/requires.txt
dj_fiobank_payments.egg-info/top_level.txt
dj_fiobank_payments/management/__init__.py
dj_fiobank_payments/management/commands/__init__.py
dj_fiobank_payments/management/commands/parse_fio_statement.py
dj_fiobank_payments/migrations/0001_initial.py
dj_fiobank_payments/migrations/0002_fiopayment_note.py
dj_fiobank_payments/migrations/__init__.py
docs/Makefile
docs/authors.rst
docs/conf.py
docs/contributing.rst
docs/history.rst
docs/index.rst
docs/installation.rst
docs/make.bat
docs/readme.rst
docs/usage.rst
tests/__init__.py
tests/models.py
tests/settings.py
tests/test_models.py
tests/test_statement.py