Metadata-Version: 1.1
Name: dj-fiobank-payments
Version: 0.3.0
Summary: Retrieve payments from Fio bank API (through fiobank package) and parse them into Payment objects.
Home-page: https://github.com/PetrDlouhy/dj-fiobank-payments
Author: Petr Dlouhý
Author-email: petr.dlouhy@email.cz
License: MIT
Keywords: dj-fiobank-payments
Platform: UNKNOWN
Classifier: Development Status :: 3 - Alpha
Classifier: Framework :: Django :: 1.11
Classifier: Framework :: Django :: 2.0
Classifier: Intended Audience :: Developers
Classifier: License :: OSI Approved :: BSD License
Classifier: Natural Language :: English
Classifier: Programming Language :: Python :: 2
Classifier: Programming Language :: Python :: 2.7
Classifier: Programming Language :: Python :: 3
Classifier: Programming Language :: Python :: 3.4
Classifier: Programming Language :: Python :: 3.5
Classifier: Programming Language :: Python :: 3.6
